datawrangler/__init__.py
datawrangler/core/__init__.py
datawrangler/core/config.ini
datawrangler/core/configurator.py
datawrangler/decorate/__init__.py
datawrangler/decorate/decorate.py
datawrangler/io/__init__.py
datawrangler/io/extension_handler.py
datawrangler/io/io.py
datawrangler/io/panda_handler.py
datawrangler/util/__init__.py
datawrangler/util/helpers.py
datawrangler/util/lazy_imports.py
datawrangler/zoo/__init__.py
datawrangler/zoo/array.py
datawrangler/zoo/dataframe.py
datawrangler/zoo/format.py
datawrangler/zoo/null.py
datawrangler/zoo/polars_dataframe.py
datawrangler/zoo/text.py
datawrangler/zoo/text_lazy.py
datawrangler/zoo/text_original.py
pydata_wrangler-0.4.0.dist-info/AUTHORS.rst
pydata_wrangler-0.4.0.dist-info/LICENSE
pydata_wrangler-0.4.0.dist-info/METADATA
pydata_wrangler-0.4.0.dist-info/WHEEL
pydata_wrangler-0.4.0.dist-info/top_level.txt
pydata_wrangler-0.4.0.dist-info/RECORD
